MANIFEST.in
setup.py
witica/__init__.py
witica/check.py
witica/log.py
witica/main.py
witica/publish.py
witica/site.py
witica/source.py
witica/test_source.py
witica/util.py
witica.egg-info/PKG-INFO
witica.egg-info/SOURCES.txt
witica.egg-info/dependency_links.txt
witica.egg-info/entry_points.txt
witica.egg-info/requires.txt
witica.egg-info/top_level.txt
witica.egg-info/zip-safe
witica/client/home.md
witica/client/meta/web.target
witica/client/meta/web/background.jpg
witica/client/meta/web/index.html
witica/client/meta/web/logo.png
witica/client/meta/web/missing.jpg
witica/client/meta/web/style.css
witica/client/meta/web/white.png
witica/client/meta/web/js/site.js
witica/client/meta/web/js/witica.js
witica/metadata/__init__.py
witica/metadata/extractor.py
witica/metadata/test_extractor.py
witica/targets/__init__.py
witica/targets/statichtml.py
witica/targets/target.py
witica/targets/test_web.py
witica/targets/web.py
witica/test/files/broken_json.md
witica/test/files/empty_title.md
witica/test/files/links.md
witica/test/files/nested_json.md
witica/test/files/no_title.md
witica/test/files/photo.jpg
witica/test/files/simple.md
witica/test/files/special_characters.md
witica/test/files/special_item_id_öäüß¡““¢≠}{|¢¶“∞…–∞œäö().md