Metadata-Version: 1.1
Name: witica
Version: 1.0.0
Summary: Automates publishing content to the Web
Home-page: witica.org
Author: Nils Breyer
Author-email: mail@witica.org
License: MIT License
Keywords: web dropbox html markdown javascript publishing incremental ftp
Platform: UNKNOWN
Classifier: License :: OSI Approved :: MIT License
Classifier: Development Status :: 3 - Alpha
Classifier: Environment :: Console
Classifier: Intended Audience :: Information Technology
Classifier: Natural Language :: English
Classifier: Operating System :: MacOS :: MacOS X
Classifier: Operating System :: POSIX :: Linux
Classifier: Programming Language :: JavaScript
Classifier: Programming Language :: Python :: 2.7
Classifier: Topic :: Internet :: WWW/HTTP
Classifier: Topic :: Text Processing :: Markup :: HTML
